structure_factor/__init__.py
structure_factor/data/__init__.py
structure_factor/data/ginibre_data.pkl
structure_factor/data/kly_data.pkl
structure_factor/data/load_data.py
structure_factor/data/poisson_data.pkl
structure_factor/data/z2_data.pkl
structure_factor/hyperuniformity.py
structure_factor/multiscale_estimators.py
structure_factor/pair_correlation_function.py
structure_factor/plotting.py
structure_factor/point_pattern.py
structure_factor/point_processes.py
structure_factor/spatial_windows.py
structure_factor/structure_factor.py
structure_factor/tapered_estimators.py
structure_factor/tapered_estimators_isotropic.py
structure_factor/tapers.py
structure_factor/transforms.py
structure_factor/utils.py
structure_factor-2.2.1.dist-info/LICENSE
structure_factor-2.2.1.dist-info/WHEEL
structure_factor-2.2.1.dist-info/METADATA
structure_factor-2.2.1.dist-info/RECORD
