Metadata-Version: 2.1
Name: structure-factor
Version: 2.2.1
Summary: Approximate the structure factor of a stationary point process, test its hyperuniformity, and identify its class of hyperuniformity.
Home-page: https://github.com/For-a-few-DPPs-more/structure-factor
License: MIT
Author: Diala Hawat
Author-email: dialahawat7@gmail.com
Maintainer: Diala Hawat
Maintainer-email: dialahawat7@gmail.com
Requires-Python: >=3.7.1,<3.10
Classifier: Intended Audience :: Science/Research
Classifier: License :: OSI Approved :: MIT License
Classifier: Programming Language :: Python :: 3
Classifier: Programming Language :: Python :: 3.8
Classifier: Programming Language :: Python :: 3.9
Classifier: Programming Language :: Python :: 3.7
Classifier: Programming Language :: Python :: 3.8
Classifier: Programming Language :: Python :: 3.9
Classifier: Topic :: Scientific/Engineering :: Mathematics
Provides-Extra: docs
Provides-Extra: notebook
Requires-Dist: Sphinx (>=4.0.3,<5.0.0) ; extra == "docs"
Requires-Dist: jupyter (>=1.0.0,<2.0.0) ; extra == "notebook"
Requires-Dist: matplotlib (>=3.4.2,<4.0.0)
Requires-Dist: notebook[jupyter] (>=6.4.12,<7.0.0)
Requires-Dist: numba (>=0.54.1,<0.55.0)
Requires-Dist: numba-scipy (>=0.3.0,<0.4.0)
Requires-Dist: numpy (>=1.20.3,<2.0.0)
Requires-Dist: pandas (>=1.2.4,<2.0.0)
Requires-Dist: pickle5 (>0.0) ; python_version >= "3.5" and python_version < "3.8"
Requires-Dist: rstcheck (>=3.3.1,<4.0.0) ; extra == "docs"
Requires-Dist: scipy (>=1.6.2,<2.0.0)
Requires-Dist: spatstat-interface (>=1.0.1,<2.0.0)
Requires-Dist: sphinx-rtd-theme (>=1.0.0,<2.0.0) ; extra == "docs"
Requires-Dist: sphinxcontrib-bibtex (>=2.4.1,<3.0.0) ; extra == "docs"
Requires-Dist: sphinxcontrib-proof (>=1.3.0,<2.0.0) ; extra == "docs"
Project-URL: Documentation, https://for-a-few-dpps-more.github.io/structure-factor/
Project-URL: Repository, https://github.com/For-a-few-DPPs-more/structure-factor
